{
  "net": {
    "241-321": {
      "Акимов Артём": [
        {"FIO": "Котельников Даниил Андреевич"},
        {"FIO": "Милосердов Николай Сергеевич"},
        {"FIO": "Ясинская Дарья Денисовна"},
        {"FIO": "Каматали Алина Аароновна"},
        {"FIO": "Андрианов Михаил Андреевич"}
      ],
      "Дубовской Роман": [
        {"FIO": "Хакимов Ойбек Хошимжон угли"},
        {"FIO": "Язалиев Тимир"}
      ],
      "Зернов Дмитрий": [
        {"FIO": "Тарашнин Алексей Александрович"},
        {"FIO": "Гречников Артем Витальевич"},
        {"FIO": "Петров Кирилл Андреевич"},
        {"FIO": "Бюдаев Юрий Сергеевич"},
        {"FIO": "Колмогоров Алексей Владимирович"}
      ],
      "Лилеков Вадим": [
        {"FIO": "Колобанов Алексей Юрьевич"},
        {"FIO": "Фролкин Александр Александрович"},
        {"FIO": "Оганесян Максим Каренович"},
        {"FIO": "Казаков Дмитрий Александрович"},
        {"FIO": "Аргунов Денис Сергеевич"},
        {"FIO": "Прокопченко Владислав Феликсович"}
      ],
      "Наврузов Рамазан": [
        {"FIO": "Музыченко Сергей Кириллович"},
        {"FIO": "Кузора Артём Владимирович"},
        {"FIO": "Болохонцев Виктор Андреевич"},
        {"FIO": "Иванилов Алексей Тимофеевич"},
        {"FIO": "Жмеренчук Александр Анатольевич"}
      ],
      "Нерсисян Артем": [
        {"FIO": "Стеценко Артём Александрович"},
        {"FIO": "Шегай Владимир Викторович"},
        {"FIO": "Раич Николай Дмитриевич"},
        {"FIO": "Хайыдов Хайдаргулы"}
      ],
      "Шораханов Тимур": [
        {"FIO": "Воротилин Илья Андреевич"},
        {"FIO": "Мамонова Ксения Дмитриевна"},
        {"FIO": "Глущенко Ульяна Александровна"},
        {"FIO": "Сычев Егор Олегович"},
        {"FIO": "Пискарев Игорь Максимович"}
      ],
      "Трубицин Вячеслав": [
        {"FIO": "Морозов Владислав Алексеевич"},
        {"FIO": "Максимов Андрей Олегович"},
        {"FIO": "Целобанов Николай Васильевич"},
        {"FIO": "Беляев Александр Алексеевич"}
      ],
      "Чердаков Анатолий": [
        {"FIO": "Нерсисян Артём Арменович"},
        {"FIO": "Гайворонский Семён Сергеевич"},
        {"FIO": "Романов Александр Дмитриевич"}
      ]
    },
    "241-3210": {
      "Акимов Артём": [
        {"FIO": "Паладий Максим Юрьевич"},
        {"FIO": "Маринина Анастасия Павловна"},
        {"FIO": "Часовских Мария Олеговна"},
        {"FIO": "Реброва Анастасия Алексеевна"}
      ],
      "Дубовской Роман": [
        {"FIO": "Мухамбетов Рустам Серкович"},
        {"FIO": "Усманов Аброрбек Икромали угли"},
        {"FIO": "Якунин Кирилл Дмитриевич"},
        {"FIO": "Вуймов Никита Олегович"},
        {"FIO": "Кушжетеров Ибрагим Хасанович"},
        {"FIO": "Хамраев Аброр Бехзодович"},
        {"FIO": "Гюндоган Хюмейра"}
      ],
      "Зернов Дмитрий": [
        {"FIO": "Колотыгин Даниил Алесеевич"},
        {"FIO": "Карлин Петр Павлович"},
        {"FIO": "Смородов Лев Николаевич"}
      ],
      "Лилеков Вадим": [
        {"FIO": "Миржалилов Жавохир Улугбек Угли"},
        {"FIO": "Шелухин Михаил Алексеевич"},
        {"FIO": "Горяев Вадим Евгеньевич"}
      ],
      "Наврузов Рамазан": [
        {"FIO": "Кузора Артём Владимирович"}
      ],
      "Шораханов Тимур": [
        {"FIO": "Воротилин Илья Андреевич"}
      ],
      "Трубицин Вячеслав": [
        {"FIO": "Морозов Владислав Алексеевич"}
      ],
      "Чердаков Анатолий": [
        {"FIO": "Нерсисян Артём Арменович"}
      ]
    }
  },
  "web": {
    "241-3210": {
      "Бастун Андрей": [
        {"FIO": "Гбелейи Эммануэль Дамилола"},
        {"FIO": "Гюндоган Хюмейра"},
        {"FIO": "Усманов Аброрбек Икромали угли"},
        {"FIO": "Хамраев Аброр Бехзодович"},
        {"FIO": "Шохрадов Азат"}
      ],
      "Бухарцев Матвей": [
        {"FIO": "Ассауп Самир Кайратович"},
        {"FIO": "Карлин Петр Павлович"},
        {"FIO": "Колотыгин Даниил Алесеевич"},
        {"FIO": "Мухамбетов Рустам Серкович"},
        {"FIO": "Шастин Андрей Александрович"}
      ],
      "Кудинов Данила": [
        {"FIO": "Вуймов Никита Олегович"},
        {"FIO": "Горяев Вадим Евгеньевич"},
        {"FIO": "Дымент Леонид Алексеевич"},
        {"FIO": "Казарихин Александр Дмитриевич"},
        {"FIO": "Каравклков Дмитрий Александрович"}
      ],
      "Мелихова Ева-София": [
        {"FIO": "Фролова Ксения Михайловна"},
        {"FIO": "Шелухин Михаил Алексеевич"},
        {"FIO": "Юлдашева Валерия Ёдгоржоновна"},
        {"FIO": "Якунин Кирилл Дмитриевич"}
      ],
      "Самойленко Марк": [
        {"FIO": "Витряк Богдан Олегович"},
        {"FIO": "Ильин Артём Русланович"},
        {"FIO": "Красноперов Сергей Александрович"},
        {"FIO": "Смородов Лев Николаевич"},
        {"FIO": "Зимин Арсений Олегович"}
      ],
      "Старцев Виталий": [
        {"FIO": "Кушжетеров Ибрагим Хасанович"},
        {"FIO": "Мамажанова Бону А'замжановна"},
        {"FIO": "Миржалилов Жавохир Улугбек Угли"},
        {"FIO": "Мохманд Марватулла"},
        {"FIO": "Нумонов Азизбек Исроилжон Угли"}
      ],
      "Хаметов Артем": [
        {"FIO": "Маринина Анастасия Павловна"},
        {"FIO": "Матязов Бабур"},
        {"FIO": "Паладий Максим Юрьевич"},
        {"FIO": "Реброва Анастасия Алексеевна"},
        {"FIO": "Часовских Мария Олеговна"}
      ],
      "Якушева Елена": [
        { "FIO": "Булытова Мария Васильевна" },
        { "FIO": "Смирнова Екатерина Сергеевна" },
        { "FIO": "Таалайбек кызы Сезим" },
        { "FIO": "Тохтаев Абдыхамут" },
        { "FIO": "Чакыр Джемиле" }
      ]
    },
    "241-321": {
      "Бастун Андрей": [
        {"FIO": "Колмогоров Алексей Владимирович"},
        {"FIO": "Колобанов Алексей Юрьевич"},
        {"FIO": "Кузора Артём Владимирович"},
        {"FIO": "Раич Николай Дмитриевич"},
        {"FIO": "Шегай Владимир Викторович"}
      ],
      "Мелихова Ева-София": [
        {"FIO": "Максимов Андрей Олегович"},
        {"FIO": "Музыченко Сергей Кириллович"},
        {"FIO": "Романов Александр Дмитриевич"},
        {"FIO": "Фролкин Александр Александрович"},
        {"FIO": "Андрианов Михаил Андреевич"},
        {"FIO": "Каматали Алина Аароновна"}
      ],
      "Бухарцев Матвей": [
        {"FIO": "Воротилин Илья Андреевич"},
        {"FIO": "Иванилов Алексей Тимофеевич"},
        {"FIO": "Милосердов Николай Сергеевич"},
        {"FIO": "Пискарев Игорь Максимович"},
        {"FIO": "Хайыдов Хайдаргулы"}
      ],
      "Кудинов Данила": [
        {"FIO": "Аргунов Денис Сергеевич"},
        {"FIO": "Бюдаев Юрий Сергеевич"},
        {"FIO": "Котельников Даниил Андреевич"},
        {"FIO": "Морозов Владислав Алексеевич"},
        {"FIO": "Тарашнин Алексей Александрович"}
      ],
      "Самойленко Марк": [
        {"FIO": "Гречников Артем Витальевич"},
        {"FIO": "Казаков Дмитрий Александрович"},
        {"FIO": "Стеценко Артём Александрович"},
        {"FIO": "Сычев Егор Олегович"},
        {"FIO": "Шарипов Артур Сергеевич"}
      ],
      "Старцев Виталий": [
        {"FIO": "Гайворонский Семён Сергеевич"},
        {"FIO": "Жмеренчук Александр Анатольевич"},
        {"FIO": "Колмогоров Алексей Владимирович"},
        {"FIO": "Оганесян Максим Каренович"},
        {"FIO": "Целобанов Николай Васильевич"}
      ],
      "Хаметов Артем": [
        {"FIO": "Мамонова Ксения Дмитриевна"},
        {"FIO": "Нерсисян Артём Арменович"},
        {"FIO": "Петров Кирилл Андреевич"},
        {"FIO": "Ясинская Дарья Денисовна"}
      ],
      "Якушева Елена": [
        {"FIO": "Глущенко Ульяна Александровна"},
        {"FIO": "Беляев Александр Алексеевич"},
        {"FIO": "Болохонцев Виктор Андреевич"},
        {"FIO": "Прокопченко Владислав Феликсович"},
        {"FIO": "Язалиев Тимир"}
      ]
    }
  }
}